MANIFEST.in
README.rst
setup.py
fbauth/__init__.py
fbauth/bootstrap.py
fbauth/helpers.py
fbauth/partials.py
fbauth/controllers/__init__.py
fbauth/controllers/root.py
fbauth/lib/__init__.py
fbauth/lib/utils.py
fbauth/migration/env.py
fbauth/migration/script.py.mako
fbauth/migration/versions/e8d522d38d3d_alter_facebook_id_length_to_utf8mb4_.py
fbauth/migration/versions/empty.txt
fbauth/model/__init__.py
fbauth/model/ming_models.py
fbauth/model/sqla_models.py
fbauth/public/__init__.py
fbauth/templates/__init__.py
tgapp_fbauth.egg-info/PKG-INFO
tgapp_fbauth.egg-info/SOURCES.txt
tgapp_fbauth.egg-info/dependency_links.txt
tgapp_fbauth.egg-info/entry_points.txt
tgapp_fbauth.egg-info/not-zip-safe
tgapp_fbauth.egg-info/requires.txt
tgapp_fbauth.egg-info/top_level.txt