Metadata-Version: 1.0
Name: tgapp-fbauth
Version: 0.3.4
Summary: Facebook Authentication for TurboGears2
Home-page: http://bitbucket.org/axant/tgapp-fbauth
Author: AXANT
Author-email: tech@axant.it
License: UNKNOWN
Keywords: turbogears2.application
Platform: UNKNOWN
